{
  "author": "a4k-openproject",
  "version": "1.1.0",
  "name": "a4kOfficial",
  "update_directory": "",
  "remote_meta": "",
  "seren_version": "2.2.0",
  "setup_extension": "configure.py",
  "services": [],
  "settings": [
    {
      "id": "justwatch.country",
      "type": "string",
      "default": "US",
      "visible": true,
      "label": "JustWatch Country"
    },
    {
      "id": "general.firstrun",
      "type": "string",
      "default": "true",
      "visible": false,
      "label": "First Run"
    }
  ]
}